[
  {
    "name": "Beats Solo Pro",
    "image": "https://i.ibb.co/wd8gqWz/h1.png",
    "brand": "Apple",
    "price": 299.99,
    "discount": 15,
    "rating": 4.5,
    "title": "On-Ear Noise Cancelling Headphones",
    "short_description": "Beats Solo Pro delivers premium sound and active noise cancellation.",
    "features": [
      "Active Noise Cancelling",
      "Transparency Mode",
      "Apple H1 Chip"
    ],
    "specifications": {
      "driver": "Custom high-excursion driver",
      "battery_life": "Up to 22 hours with ANC and Transparency mode off"
    },
    "category": "Headphones"
  },
  {
    "name": "Apple Watch Series 7",
    "image": "https://i.ibb.co/2W604Zd/watch-5.png",
    "brand": "Apple",
    "price": 449.99,
    "discount": 12,
    "rating": 4.5,
    "title": "Advanced Smartwatch with Always-On Display",
    "short_description": "Stay connected and track your fitness with Apple Watch Series 7.",
    "features": [
      "Always-On Retina Display",
      "Blood Oxygen Sensor",
      "Sleep Tracking"
    ],
    "specifications": {
      "display": "Always-On Retina LTPO OLED display",
      "water_resistance": "Water-resistant up to 50 meters"
    },
    "category": "Watch"
  },
  {
    "name": "Apple Watch SE",
    "image": "https://i.ibb.co/0DxCRL7/watch-4.png",
    "brand": "Apple",
    "price": 279.99,
    "discount": 10,
    "rating": 4.5,
    "title": "Affordable Smartwatch with Essential Features",
    "short_description": "Stay connected and active with Apple Watch SE.",
    "features": [
      "Retina Display",
      "Fall Detection",
      "Fitness and Health Tracking"
    ],
    "specifications": {
      "display": "Retina LTPO OLED display",
      "water_resistance": "Water-resistant up to 50 meters"
    },
    "category": "Watch"
  },
  {
    "name": "Apple Watch Series 3",
    "image": "https://i.ibb.co/j5bLKxM/watch-3.png",
    "brand": "Apple",
    "price": 199.99,
    "discount": 8,
    "rating": 4.5,
    "title": "Smartwatch with GPS",
    "short_description": "Basic smartwatch with built-in GPS for fitness tracking.",
    "features": ["Retina Display", "Built-in GPS", "Swimproof Design"],
    "specifications": {
      "display": "Retina OLED display",
      "water_resistance": "Water-resistant up to 50 meters"
    },
    "category": "Watch"
  },
  {
    "name": "MacBook Air M2",
    "image": "https://i.ibb.co/G7hH6B2/apple-1.png",
    "brand": "Apple",
    "price": 1199.99,
    "discount": 8,
    "rating": 4.5,
    "title": "Ultra-Portable Laptop with M2 Chip",
    "short_description": "Powerful and lightweight MacBook Air with the latest M2 chip.",
    "features": ["Retina Display", "M2 Chip", "Touch ID"],
    "specifications": {
      "processor": "Apple M2 Chip",
      "memory": "16GB RAM, 512GB SSD"
    },
    "category": "Laptops"
  },
  {
    "name": "MacBook Pro 16-inch",
    "image": "https://i.ibb.co/jLmsnWh/mac-3.png",
    "brand": "Apple",
    "price": 2399.99,
    "discount": 5,
    "rating": 4.5,
    "title": "Powerful Laptop for Professionals",
    "short_description": "Experience the ultimate performance with MacBook Pro 16-inch.",
    "features": [
      "Retina Display",
      "Intel Core i9 Processor",
      "AMD Radeon Pro 5500M Graphics"
    ],
    "specifications": {
      "processor": "2.3GHz 8-core Intel Core i9",
      "memory": "16GB RAM, 1TB SSD"
    },
    "category": "Laptops"
  },
  {
    "name": "Huawei FreeBuds Pro",
    "image": "https://i.ibb.co/zVNG8nZ/h2.png",
    "brand": "Huawei",
    "price": 179.99,
    "discount": 15,
    "rating": 4.5,
    "title": "True Wireless Noise-Canceling Earbuds",
    "short_description": "Experience immersive sound with Huawei FreeBuds Pro.",
    "features": [
      "Active Noise Cancellation",
      "Dual Connection",
      "Touch Control"
    ],
    "specifications": {
      "driver": "11mm dynamic driver",
      "battery_life": "Up to 7 hours of playback on a single charge"
    },
    "category": "Headphones"
  },
  {
    "name": "Huawei FreeLace Pro",
    "image": "https://i.ibb.co/VJ9749H/h3.png",
    "brand": "Huawei",
    "price": 99.99,
    "discount": 10,
    "rating": 4.5,
    "title": "Wireless Noise-Canceling Earphones",
    "short_description": "Enjoy high-quality sound with Huawei FreeLace Pro.",
    "features": [
      "Active Noise Cancellation",
      "HiPair Technology",
      "Long Battery Life"
    ],
    "specifications": {
      "driver": "14.2mm dynamic driver",
      "battery_life": "Up to 24 hours of playback on a single charge"
    },
    "category": "Headphones"
  },
  {
    "name": "Huawei Watch GT 3",
    "image": "https://i.ibb.co/CnDR17X/watch-2.png",
    "brand": "Huawei",
    "price": 279.99,
    "discount": 10,
    "rating": 4.5,
    "title": "Smartwatch with Long Battery Life",
    "short_description": "Stay connected and monitor your health with Huawei Watch GT 3.",
    "features": ["AMOLED Display", "2-Week Battery Life", "SpO2 Monitoring"],
    "specifications": {
      "display": "1.43-inch AMOLED touchscreen",
      "battery_life": "Up to 14 days of typical usage"
    },
    "category": "Watch"
  },
  {
    "name": "Huawei Watch Fit",
    "image": "https://i.ibb.co/FY9jSFG/watch-1.png",
    "brand": "Huawei",
    "price": 129.99,
    "discount": 8,
    "rating": 4.5,
    "title": "Slim Fitness Smartwatch",
    "short_description": "Stay fit and stylish with Huawei Watch Fit.",
    "features": ["AMOLED Display", "SpO2 Monitoring", "96 Workout Modes"],
    "specifications": {
      "display": "1.64-inch AMOLED touchscreen",
      "battery_life": "Up to 10 days of typical usage"
    },
    "category": "Watch"
  },
  {
    "name": "Huawei MateBook X Pro",
    "image": "https://i.ibb.co/MN1kLMf/m-1.png",
    "brand": "Huawei",
    "price": 1499.99,
    "discount": 8,
    "rating": 4.5,
    "title": "Slim and Powerful Laptop",
    "short_description": "Huawei MateBook X Pro delivers high performance in a slim design.",
    "features": [
      "3K LTPS Display",
      "Intel Core i7 Processor",
      "NVIDIA GeForce MX250 GPU"
    ],
    "specifications": {
      "processor": "10th Gen Intel Core i7-10510U",
      "memory": "16GB RAM, 1TB SSD"
    },
    "category": "Laptops"
  },
  {
    "name": "Huawei MateBook D 15",
    "image": "https://i.ibb.co/N2tGTT8/m-2.png",
    "brand": "Huawei",
    "price": 699.99,
    "discount": 6,
    "rating": 4.5,
    "title": "Budget-Friendly Laptop",
    "short_description": "Huawei MateBook D 15 offers performance on a budget.",
    "features": [
      "Full HD Display",
      "AMD Ryzen 5 Processor",
      "Thin and Lightweight"
    ],
    "specifications": {
      "processor": "AMD Ryzen 5 3500U",
      "memory": "8GB RAM, 256GB SSD"
    },
    "category": "Laptops"
  },
  {
    "name": "HP Spectre x360 13",
    "image": "https://i.ibb.co/M6SpMbw/m-3.png",
    "brand": "HP",
    "price": 1099.99,
    "discount": 10,
    "rating": 4.5,
    "title": "Premium Convertible Laptop",
    "short_description": "Experience versatility and performance with HP Spectre x360 13.",
    "features": [
      "13.3-inch 4K OLED Touchscreen",
      "Intel Core i7 Processor",
      "512GB SSD"
    ],
    "specifications": {
      "processor": "Intel Core i7-1165G7",
      "memory": "16GB RAM"
    },
    "category": "Laptops"
  },
  {
    "name": "HP Envy 15",
    "image": "https://i.ibb.co/G7hH6B2/apple-1.png",
    "brand": "HP",
    "price": 999.99,
    "discount": 8,
    "rating": 4.5,
    "title": "Elegant High-Performance Laptop",
    "short_description": "Elevate your computing experience with the HP Envy 15.",
    "features": [
      "15.6-inch 4K OLED Display",
      "Intel Core i7 Processor",
      "1TB SSD"
    ],
    "specifications": {
      "processor": "Intel Core i7-10750H",
      "memory": "16GB RAM"
    },
    "category": "Laptops"
  },
  {
    "name": "HP Pavilion 14",
    "image": "https://i.ibb.co/8Dn1nkz/m-5.png",
    "brand": "HP",
    "price": 599.99,
    "discount": 6,
    "rating": 4.5,
    "title": "Affordable Everyday Laptop",
    "short_description": "Get things done with the reliable HP Pavilion 14.",
    "features": [
      "14-inch Full HD Display",
      "AMD Ryzen 5 Processor",
      "256GB SSD"
    ],
    "specifications": {
      "processor": "AMD Ryzen 5 4500U",
      "memory": "8GB RAM"
    },
    "category": "Laptops"
  },
  {
    "name": "HP Omen 15",
    "image": "https://i.ibb.co/NFzgWmZ/l3.png",
    "brand": "HP",
    "price": 1199.99,
    "discount": 12,
    "rating": 4.5,
    "title": "Gaming Laptop with NVIDIA RTX Graphics",
    "short_description": "Dominate in games with the power of the HP Omen 15.",
    "features": [
      "15.6-inch 144Hz FHD Display",
      "Intel Core i7 Processor",
      "512GB SSD"
    ],
    "specifications": {
      "processor": "Intel Core i7-10750H",
      "memory": "16GB RAM, 512GB SSD"
    },
    "category": "Laptops"
  },
  {
    "name": "HP ZBook 15 G6",
    "image": "https://i.ibb.co/8Dn1nkz/m-5.png",
    "brand": "HP",
    "price": 1799.99,
    "discount": 15,
    "rating": 4.5,
    "title": "Mobile Workstation for Professionals",
    "short_description": "Power and reliability for professional work with HP ZBook 15 G6.",
    "features": [
      "15.6-inch 4K DreamColor Display",
      "Intel Xeon Processor",
      "1TB SSD"
    ],
    "specifications": {
      "processor": "Intel Xeon E-2276M",
      "memory": "32GB RAM, 1TB SSD"
    },
    "category": "Laptops"
  },
  {
    "name": "HP Chromebook 14",
    "image": "https://i.ibb.co/XbgJrtm/m-6.png",
    "brand": "HP",
    "price": 279.99,
    "discount": 5,
    "rating": 4.5,
    "title": "Affordable Chrome OS Laptop",
    "short_description": "Simplicity and value with the HP Chromebook 14.",
    "features": [
      "14-inch Full HD Touchscreen",
      "Intel Celeron Processor",
      "64GB eMMC"
    ],
    "specifications": {
      "processor": "Intel Celeron N4000",
      "memory": "4GB RAM, 64GB eMMC"
    },
    "category": "Laptops"
  },
  {
    "name": "Dell XPS 13",
    "image": "https://i.ibb.co/jLmsnWh/mac-3.png",
    "brand": "Dell",
    "price": 1299.99,
    "discount": 10,
    "rating": 4.5,
    "title": "Premium Ultrabook",
    "short_description": "Experience incredible performance with the Dell XPS 13.",
    "features": [
      "13.4-inch 4K Ultra HD+ InfinityEdge Touch Display",
      "Intel Core i7 Processor",
      "512GB SSD"
    ],
    "specifications": {
      "processor": "Intel Core i7-1165G7",
      "memory": "16GB RAM"
    },
    "category": "Laptops"
  },
  {
    "name": "Dell Inspiron 15",
    "image": "https://i.ibb.co/KLYK8gN/l1.png",
    "brand": "Dell",
    "price": 899.99,
    "discount": 8,
    "rating": 4.5,
    "title": "Versatile Everyday Laptop",
    "short_description": "Stay productive and entertained with Dell Inspiron 15.",
    "features": [
      "15.6-inch Full HD Touch Display",
      "Intel Core i5 Processor",
      "256GB SSD"
    ],
    "specifications": {
      "processor": "Intel Core i5-1135G7",
      "memory": "8GB RAM"
    },
    "category": "Laptops"
  },
  {
    "name": "Dell Latitude 14",
    "image": "https://i.ibb.co/G7hH6B2/apple-1.png",
    "brand": "Dell",
    "price": 1099.99,
    "discount": 6,
    "rating": 4.5,
    "title": "Business Laptop with Security Features",
    "short_description": "Secure and reliable computing for business needs with Dell Latitude 14.",
    "features": [
      "14-inch Full HD Display",
      "Intel Core i5 Processor",
      "256GB SSD"
    ],
    "specifications": {
      "processor": "Intel Core i5-10310U",
      "memory": "8GB RAM"
    },
    "category": "Laptops"
  },
  {
    "name": "Dell G5 15",
    "image": "https://i.ibb.co/NFzgWmZ/l3.png",
    "brand": "Dell",
    "price": 1199.99,
    "discount": 12,
    "rating": 4.5,
    "title": "Gaming Laptop with NVIDIA GTX Graphics",
    "short_description": "Immerse in gaming experiences with the power of Dell G5 15.",
    "features": [
      "15.6-inch 120Hz FHD Display",
      "Intel Core i7 Processor",
      "512GB SSD",
      "NVIDIA GeForce GTX 1650 Ti GPU"
    ],
    "specifications": {
      "processor": "Intel Core i7-10750H",
      "memory": "16GB RAM"
    },
    "category": "Laptops"
  },
  {
    "name": "Dell Precision 5550",
    "image": "https://i.ibb.co/KLYK8gN/l1.png",
    "brand": "Dell",
    "price": 1999.99,
    "discount": 15,
    "rating": 4.5,
    "title": "Mobile Workstation for Professionals",
    "short_description": "High-performance workstation for demanding professional tasks.",
    "features": [
      "15.6-inch 4K Ultra HD+ InfinityEdge Display",
      "Intel Core i9 Processor",
      "1TB SSD",
      "NVIDIA Quadro T2000 GPU"
    ],
    "specifications": {
      "processor": "Intel Core i9-10885H",
      "memory": "32GB RAM"
    },
    "category": "Laptops"
  },
  {
    "name": "Dell Chromebook 14",
    "image": "https://i.ibb.co/Ss1TSmj/l5.png",
    "brand": "Dell",
    "price": 299.99,
    "discount": 5,
    "rating": 4.5,
    "title": "Simple and Secure Chrome OS Laptop",
    "short_description": "Effortless computing with Dell Chromebook 14 running Chrome OS.",
    "features": [
      "14-inch Full HD Display",
      "Intel Celeron Processor",
      "64GB eMMC"
    ],
    "specifications": {
      "processor": "Intel Celeron N4020",
      "memory": "4GB RAM"
    },
    "category": "Laptops"
  },
  {
    "name": "MI AirDots Pro 2",
    "image": "https://i.ibb.co/YPN7hww/h-4.png",
    "brand": "MI",
    "price": 79.99,
    "discount": 10,
    "rating": 4.5,
    "title": "Wireless Earbuds with Active Noise Cancellation",
    "short_description": "Enjoy high-quality sound and noise cancellation with MI AirDots Pro 2.",
    "features": [
      "Active Noise Cancellation",
      "Dual Microphones",
      "Touch Controls"
    ],
    "specifications": {
      "driver": "14.2mm dynamic driver",
      "battery_life": "Up to 5 hours of playback on a single charge"
    },
    "category": "Headphones"
  },
  {
    "name": "MI Redmi Note 10 Pro",
    "image": "https://i.ibb.co/NnBp2nj/m-1.webp",
    "brand": "MI",
    "price": 249.99,
    "discount": 8,
    "rating": 4.6,
    "title": "Pro Camera Smartphone",
    "short_description": "Capture stunning photos with the MI Redmi Note 10 Pro's pro-grade camera system.",
    "features": [
      "108MP Quad Camera",
      "6.67-inch AMOLED Display",
      "5,020mAh Battery"
    ],
    "specifications": {
      "display": "6.67-inch AMOLED display",
      "camera": "108MP + 8MP + 5MP + 2MP Quad Camera"
    },
    "category": "Smartphones"
  },
  {
    "name": "MI Smart Band 6",
    "image": "https://i.ibb.co/FY9jSFG/watch-1.png",
    "brand": "MI",
    "price": 39.99,
    "discount": 10,
    "rating": 4.4,
    "title": "Fitness Tracker with Large Display",
    "short_description": "Track your fitness and health with the MI Smart Band 6's large AMOLED display.",
    "features": [
      "1.56-inch AMOLED Display",
      "Heart Rate Monitoring",
      "Waterproof"
    ],
    "specifications": {
      "display": "1.56-inch AMOLED touchscreen",
      "water_resistance": "Water-resistant up to 50 meters"
    },
    "category": "Watch"
  },
  {
    "name": "Xiaomi Redmi Note 9 Pro",
    "image": "https://i.ibb.co/6bfsyfs/mobile-3.png",
    "brand": "Xiaomi",
    "price": 229.99,
    "discount": 10,
    "rating": 4.5,
    "title": "Pro Camera Smartphone",
    "short_description": "Capture incredible photos with Redmi Note 9 Pro's advanced camera system.",
    "features": [
      "64MP Quad Camera",
      "6.67-inch IPS LCD Display",
      "5,020mAh Battery"
    ],
    "specifications": {
      "display": "6.67-inch IPS LCD display",
      "camera": "64MP + 8MP + 5MP + 2MP Quad Camera"
    },
    "category": "Smartphones"
  },
  {
    "name": "Xiaomi Redmi Note 11 Pro",
    "image": "https://i.ibb.co/MRc1Lfk/mobile-2.png",
    "brand": "Samsung",
    "price": 799.99,
    "discount": 15,
    "rating": 4.8,
    "title": "High-End Smartphone",
    "short_description": "Experience cutting-edge technology with the Samsung Galaxy S21.",
    "features": [
      "64MP Triple Camera",
      "6.2-inch Dynamic AMOLED Display",
      "5G Capable"
    ],
    "specifications": {
      "display": "6.2-inch Dynamic AMOLED display",
      "camera": "64MP + 12MP + 12MP Triple Camera"
    },
    "category": "Smartphones"
  },
  {
    "name": "Lenovo Legion Y740",
    "image": "https://i.ibb.co/CPMb3NX/l4.png",
    "brand": "Lenovo",
    "price": 1499.99,
    "discount": 10,
    "rating": 4.7,
    "title": "High-Performance Gaming Laptop",
    "short_description": "Dominate your games with Lenovo Legion Y740's powerful hardware and stunning display.",
    "features": [
      "Intel Core i7-9750H Processor",
      "NVIDIA GeForce RTX 2060 GPU",
      "16GB RAM"
    ],
    "specifications": {
      "processor": "Intel Core i7-9750H",
      "memory": "16GB RAM, 512GB SSD"
    },
    "category": "Laptops"
  },
  {
    "name": "Lenovo ThinkPad X1 Carbon",
    "image": "https://i.ibb.co/NFzgWmZ/l3.png",
    "brand": "Lenovo",
    "price": 1299.99,
    "discount": 8,
    "rating": 4.8,
    "title": "Premium Business Ultrabook",
    "short_description": "Achieve maximum productivity with Lenovo ThinkPad X1 Carbon's sleek design and robust performance.",
    "features": [
      "Intel Core i5-8265U Processor",
      "14-inch 4K HDR Display",
      "16GB RAM"
    ],
    "specifications": {
      "processor": "Intel Core i5-8265U",
      "memory": "16GB RAM, 256GB NVMe SSD"
    },
    "category": "Laptops"
  },
  {
    "name": "Lenovo Tab P11 Pro",
    "image": "https://i.ibb.co/3YZCwNP/l2.png",
    "brand": "Lenovo",
    "price": 499.99,
    "discount": 5,
    "rating": 4.6,
    "title": "High-End Android Tablet",
    "short_description": "Immerse yourself in entertainment with Lenovo Tab P11 Pro's stunning OLED display and powerful speakers.",
    "features": [
      "11.5-inch 2K OLED Display",
      "Quad Speakers with Dolby Atmos",
      "Snapdragon 730G Processor"
    ],
    "specifications": {
      "display": "11.5-inch 2K OLED touchscreen",
      "audio": "Quad JBL Speakers with Dolby Atmos"
    },
    "category": "Laptops"
  },
  {
    "name": "Lenovo IdeaPad Flex 5",
    "image": "https://i.ibb.co/KLYK8gN/l1.png",
    "brand": "Lenovo",
    "price": 699.99,
    "discount": 6,
    "rating": 4.5,
    "title": "Versatile 2-in-1 Laptop",
    "short_description": "Stay productive and creative with Lenovo IdeaPad Flex 5's flexible design and powerful performance.",
    "features": [
      "AMD Ryzen 5 4500U Processor",
      "14-inch Full HD IPS Touchscreen",
      "8GB RAM"
    ],
    "specifications": {
      "processor": "AMD Ryzen 5 4500U",
      "memory": "8GB RAM, 256GB NVMe SSD"
    },
    "category": "Laptops"
  }
]
